reliqua/__init__.py
reliqua/api.py
reliqua/app.py
reliqua/auth.py
reliqua/database.py
reliqua/docs.py
reliqua/exceptions.py
reliqua/media_handlers.py
reliqua/middleware.py
reliqua/openapi.py
reliqua/sphinx_parser.py
reliqua/status_codes.py
reliqua/swagger.py
reliqua/resources/__init__.py
reliqua/resources/base.py
reliqua/swagger/favicon-16x16.png
reliqua/swagger/favicon-32x32.png
reliqua/swagger/index.html
reliqua/swagger/oauth2-redirect.html
reliqua/swagger/swagger-ui-bundle.js
reliqua/swagger/swagger-ui-bundle.js.map
reliqua/swagger/swagger-ui-standalone-preset.js
reliqua/swagger/swagger-ui-standalone-preset.js.map
reliqua/swagger/swagger-ui.css
reliqua/swagger/swagger-ui.css.map
reliqua/swagger/swagger-ui.js
reliqua/swagger/swagger-ui.js.map
reliqua-0.0.13.dist-info/licenses/LICENSE
reliqua-0.0.13.dist-info/METADATA
reliqua-0.0.13.dist-info/WHEEL
reliqua-0.0.13.dist-info/top_level.txt
reliqua-0.0.13.dist-info/RECORD
