Metadata-Version: 2.4
Name: reliqua
Version: 0.0.13
Summary: Simple, efficient, intuitive API Framework
Author-email: Terrence Meiczinger <terrence72@gmail.com>
License: MIT
Project-URL: homepage, https://github.com/tmeiczin/reliqua
Project-URL: documentation, https://github.com/tmeiczin/reliqua
Project-URL: repository, https://github.com/tmeiczin/reliqua
Keywords: utilities
Classifier: Development Status :: 4 - Beta
Classifier: Intended Audience :: Developers
Classifier: Operating System :: Unix
Classifier: Operating System :: POSIX
Classifier: Operating System :: MacOS
Classifier: Operating System :: Microsoft :: Windows
Classifier: Programming Language :: Python :: 3
Classifier: Programming Language :: Python :: Implementation :: CPython
Classifier: Programming Language :: Python :: Implementation :: PyPy
Classifier: Topic :: Internet :: WWW/HTTP :: HTTP Servers
Classifier: License :: OSI Approved :: MIT License
Requires-Python: >=3.8
License-File: LICENSE
Requires-Dist: falcon>=3.0.0
Requires-Dist: falcon-cors
Requires-Dist: gunicorn>=19.6.0
Requires-Dist: pyyaml
Provides-Extra: dev
Requires-Dist: tox; extra == "dev"
Requires-Dist: requests; extra == "dev"
Requires-Dist: bump2version; extra == "dev"
Dynamic: license-file
